Workbook

Sheet READ ME
A1: FBM Launch Toolkit
A2: Companion to "Sell on Amazon Canada Without Touching Inventory" by Rujal Tuladhar
A4: Tab | B4: What it does
A5: Settings | B5: Your fee %, drop-ship fee, shipping cost and profit floor. Every other tab reads from here. Change these first.
A6: Profit Calculator | B6: One row per ASIN. Enter supplier price, pack sizes and the competitor total; the sheet computes your price split, fees and PASS/FAIL against your floor (Chapter 4).
A7: Research Tracker | B7: The research pipeline log: brand gating status, UPC, ASINs found, sellers, FBA present, decision (Chapter 5).
A8: Repricing Audit | B8: The fortnightly Featured Offer audit: my total vs featured total, match price, profit at match, MATCH or HOLD (Chapter 7).
A9: Order Log | B9: Amazon order ID, PO (last 7 digits), supplier reference, tracking, confirmed date. The weekly reconciliation lives here (Chapter 8).
A10: Monthly Report | B10: The one-page profit report (Chapter 11).
A11: 30-Day Plan | B11: The launch checklist from Chapter 13 with a done column.

Sheet Settings
A1: Setting | B1: Value | C1: Note
A2: Referral fee % | B2: 0.18 | C2: Budget above the published category rate (book uses 18%)
A3: Drop-ship fee, order under $100 | B3: 9.95 | C3: From your supplier rate card
A4: Drop-ship fee, order $100 and over | B4: 4.95
A5: Drop-ship fee threshold | B5: 100
A6: Outbound shipping (supplier ships to customer) | B6: 12 | C6: Shown as the shipping line on every listing
A7: Self-ship cost for broken-case orders | B7: 18 | C7: When the case comes to you and you ship one unit
A8: Minimum profit per unit (the floor) | B8: 10 | C8: Never list below this

Sheet Profit Calculator
A1: ASIN | B1: Title | C1: Supplier SKU | D1: Supplier price (per supplier pack) | E1: Units per supplier pack | F1: Units per Amazon listing | G1: Broken case? (Y/N) | H1: Competitor lowest TOTAL | I1: My shipping line | J1: My item price | K1: My total | L1: Referral fee | M1: Supplier cost for this listing | N1: Drop-ship fee | O1: Shipping cost to me | P1: Profit | Q1: PASS / FAIL
A2: B0EXAMPLE1 | B2: Example: adult briefs, case of 4 packs | C2: 12345 | D2: 185 | E2: 1 | F2: 1 | G2: N | H2: 319 | I2: =IF(G2="Y",0,Settings!$B$6) | J2: =IF(H2="","",H2-I2) | K2: =IF(J2="","",J2+I2) | L2: =IF(K2="","",K2*Settings!$B$2) | M2: =IF(D2="","",D2/E2*F2) | N2: =IF(K2="","",IF(G2="Y",0,IF(D2<Settings!$B$5,Settings!$B$3,Settings!$B$4))) | O2: =IF(K2="","",IF(G2="Y",Settings!$B$7,Settings!$B$6)) | P2: =IF(K2="","",K2-L2-M2-N2-O2) | Q2: =IF(P2="","",IF(P2>=Settings!$B$8,"PASS","FAIL"))
I3: =IF(G3="Y",0,Settings!$B$6) | J3: =IF(H3="","",H3-I3) | K3: =IF(J3="","",J3+I3) | L3: =IF(K3="","",K3*Settings!$B$2) | M3: =IF(D3="","",D3/E3*F3) | N3: =IF(K3="","",IF(G3="Y",0,IF(D3<Settings!$B$5,Settings!$B$3,Settings!$B$4))) | O3: =IF(K3="","",IF(G3="Y",Settings!$B$7,Settings!$B$6)) | P3: =IF(K3="","",K3-L3-M3-N3-O3) | Q3: =IF(P3="","",IF(P3>=Settings!$B$8,"PASS","FAIL"))
I4: =IF(G4="Y",0,Settings!$B$6) | J4: =IF(H4="","",H4-I4) | K4: =IF(J4="","",J4+I4) | L4: =IF(K4="","",K4*Settings!$B$2) | M4: =IF(D4="","",D4/E4*F4) | N4: =IF(K4="","",IF(G4="Y",0,IF(D4<Settings!$B$5,Settings!$B$3,Settings!$B$4))) | O4: =IF(K4="","",IF(G4="Y",Settings!$B$7,Settings!$B$6)) | P4: =IF(K4="","",K4-L4-M4-N4-O4) | Q4: =IF(P4="","",IF(P4>=Settings!$B$8,"PASS","FAIL"))
I5: =IF(G5="Y",0,Settings!$B$6) | J5: =IF(H5="","",H5-I5) | K5: =IF(J5="","",J5+I5) | L5: =IF(K5="","",K5*Settings!$B$2) | M5: =IF(D5="","",D5/E5*F5) | N5: =IF(K5="","",IF(G5="Y",0,IF(D5<Settings!$B$5,Settings!$B$3,Settings!$B$4))) | O5: =IF(K5="","",IF(G5="Y",Settings!$B$7,Settings!$B$6)) | P5: =IF(K5="","",K5-L5-M5-N5-O5) | Q5: =IF(P5="","",IF(P5>=Settings!$B$8,"PASS","FAIL"))
I6: =IF(G6="Y",0,Settings!$B$6) | J6: =IF(H6="","",H6-I6) | K6: =IF(J6="","",J6+I6) | L6: =IF(K6="","",K6*Settings!$B$2) | M6: =IF(D6="","",D6/E6*F6) | N6: =IF(K6="","",IF(G6="Y",0,IF(D6<Settings!$B$5,Settings!$B$3,Settings!$B$4))) | O6: =IF(K6="","",IF(G6="Y",Settings!$B$7,Settings!$B$6)) | P6: =IF(K6="","",K6-L6-M6-N6-O6) | Q6: =IF(P6="","",IF(P6>=Settings!$B$8,"PASS","FAIL"))
I7: =IF(G7="Y",0,Settings!$B$6) | J7: =IF(H7="","",H7-I7) | K7: =IF(J7="","",J7+I7) | L7: =IF(K7="","",K7*Settings!$B$2) | M7: =IF(D7="","",D7/E7*F7) | N7: =IF(K7="","",IF(G7="Y",0,IF(D7<Settings!$B$5,Settings!$B$3,Settings!$B$4))) | O7: =IF(K7="","",IF(G7="Y",Settings!$B$7,Settings!$B$6)) | P7: =IF(K7="","",K7-L7-M7-N7-O7) | Q7: =IF(P7="","",IF(P7>=Settings!$B$8,"PASS","FAIL"))
I8: =IF(G8="Y",0,Settings!$B$6) | J8: =IF(H8="","",H8-I8) | K8: =IF(J8="","",J8+I8) | L8: =IF(K8="","",K8*Settings!$B$2) | M8: =IF(D8="","",D8/E8*F8) | N8: =IF(K8="","",IF(G8="Y",0,IF(D8<Settings!$B$5,Settings!$B$3,Settings!$B$4))) | O8: =IF(K8="","",IF(G8="Y",Settings!$B$7,Settings!$B$6)) | P8: =IF(K8="","",K8-L8-M8-N8-O8) | Q8: =IF(P8="","",IF(P8>=Settings!$B$8,"PASS","FAIL"))
I9: =IF(G9="Y",0,Settings!$B$6) | J9: =IF(H9="","",H9-I9) | K9: =IF(J9="","",J9+I9) | L9: =IF(K9="","",K9*Settings!$B$2) | M9: =IF(D9="","",D9/E9*F9) | N9: =IF(K9="","",IF(G9="Y",0,IF(D9<Settings!$B$5,Settings!$B$3,Settings!$B$4))) | O9: =IF(K9="","",IF(G9="Y",Settings!$B$7,Settings!$B$6)) | P9: =IF(K9="","",K9-L9-M9-N9-O9) | Q9: =IF(P9="","",IF(P9>=Settings!$B$8,"PASS","FAIL"))
I10: =IF(G10="Y",0,Settings!$B$6) | J10: =IF(H10="","",H10-I10) | K10: =IF(J10="","",J10+I10) | L10: =IF(K10="","",K10*Settings!$B$2) | M10: =IF(D10="","",D10/E10*F10) | N10: =IF(K10="","",IF(G10="Y",0,IF(D10<Settings!$B$5,Settings!$B$3,Settings!$B$4))) | O10: =IF(K10="","",IF(G10="Y",Settings!$B$7,Settings!$B$6)) | P10: =IF(K10="","",K10-L10-M10-N10-O10) | Q10: =IF(P10="","",IF(P10>=Settings!$B$8,"PASS","FAIL"))
I11: =IF(G11="Y",0,Settings!$B$6) | J11: =IF(H11="","",H11-I11) | K11: =IF(J11="","",J11+I11) | L11: =IF(K11="","",K11*Settings!$B$2) | M11: =IF(D11="","",D11/E11*F11) | N11: =IF(K11="","",IF(G11="Y",0,IF(D11<Settings!$B$5,Settings!$B$3,Settings!$B$4))) | O11: =IF(K11="","",IF(G11="Y",Settings!$B$7,Settings!$B$6)) | P11: =IF(K11="","",K11-L11-M11-N11-O11) | Q11: =IF(P11="","",IF(P11>=Settings!$B$8,"PASS","FAIL"))
I12: =IF(G12="Y",0,Settings!$B$6) | J12: =IF(H12="","",H12-I12) | K12: =IF(J12="","",J12+I12) | L12: =IF(K12="","",K12*Settings!$B$2) | M12: =IF(D12="","",D12/E12*F12) | N12: =IF(K12="","",IF(G12="Y",0,IF(D12<Settings!$B$5,Settings!$B$3,Settings!$B$4))) | O12: =IF(K12="","",IF(G12="Y",Settings!$B$7,Settings!$B$6)) | P12: =IF(K12="","",K12-L12-M12-N12-O12) | Q12: =IF(P12="","",IF(P12>=Settings!$B$8,"PASS","FAIL"))
I13: =IF(G13="Y",0,Settings!$B$6) | J13: =IF(H13="","",H13-I13) | K13: =IF(J13="","",J13+I13) | L13: =IF(K13="","",K13*Settings!$B$2) | M13: =IF(D13="","",D13/E13*F13) | N13: =IF(K13="","",IF(G13="Y",0,IF(D13<Settings!$B$5,Settings!$B$3,Settings!$B$4))) | O13: =IF(K13="","",IF(G13="Y",Settings!$B$7,Settings!$B$6)) | P13: =IF(K13="","",K13-L13-M13-N13-O13) | Q13: =IF(P13="","",IF(P13>=Settings!$B$8,"PASS","FAIL"))
I14: =IF(G14="Y",0,Settings!$B$6) | J14: =IF(H14="","",H14-I14) | K14: =IF(J14="","",J14+I14) | L14: =IF(K14="","",K14*Settings!$B$2) | M14: =IF(D14="","",D14/E14*F14) | N14: =IF(K14="","",IF(G14="Y",0,IF(D14<Settings!$B$5,Settings!$B$3,Settings!$B$4))) | O14: =IF(K14="","",IF(G14="Y",Settings!$B$7,Settings!$B$6)) | P14: =IF(K14="","",K14-L14-M14-N14-O14) | Q14: =IF(P14="","",IF(P14>=Settings!$B$8,"PASS","FAIL"))
... I201: =IF(G201="Y",0,Settings!$B$6) | J201: =IF(H201="","",H201-I201) | K201: =IF(J201="","",J201+I201) | L201: =IF(K201="","",K201*Settings!$B$2) | M201: =IF(D201="","",D201/E201*F201) | N201: =IF(K201="","",IF(G201="Y",0,IF(D201<Settings!$B$5,Settings!$B$3,Settings!$B$4))) | O201: =IF(K201="","",IF(G201="Y",Settings!$B$7,Settings!$B$6)) | P201: =IF(K201="","",K201-L201-M201-N201-O201) | Q201: =IF(P201="","",IF(P201>=Settings!$B$8,"PASS","FAIL"))

Sheet Research Tracker
A1: Date | B1: Brand | C1: Gating status (Approved / Gated / Applied) | D1: Supplier SKU | E1: UPC | F1: Product | G1: ASIN(s) found | H1: Lowest total | I1: Seller count | J1: FBA seller present? (Y/N) | K1: Already live on this ASIN? (Y/N) | L1: Profit (from calculator) | M1: Decision (List / Skip / Recheck later) | N1: Notes

Sheet Repricing Audit
A1: Audit date | B1: ASIN | C1: SKU | D1: My item price | E1: My shipping | F1: My total | G1: Featured Offer total | H1: Am I featured? (Y/N) | I1: Price to match (featured - shipping) | J1: Supplier price | K1: Drop-ship fee | L1: Referral fee at match | M1: Profit at match | N1: MATCH / HOLD | O1: New price set
E2: =IF(D2="","",Settings!$B$6) | F2: =IF(D2="","",D2+E2) | I2: =IF(G2="","",G2-Settings!$B$6) | K2: =IF(J2="","",IF(J2<Settings!$B$5,Settings!$B$3,Settings!$B$4)) | L2: =IF(G2="","",G2*Settings!$B$2) | M2: =IF(OR(G2="",J2=""),"",G2-L2-J2-K2-Settings!$B$6) | N2: =IF(M2="","",IF(H2="Y","OK",IF(M2>=Settings!$B$8,"MATCH","HOLD")))
E3: =IF(D3="","",Settings!$B$6) | F3: =IF(D3="","",D3+E3) | I3: =IF(G3="","",G3-Settings!$B$6) | K3: =IF(J3="","",IF(J3<Settings!$B$5,Settings!$B$3,Settings!$B$4)) | L3: =IF(G3="","",G3*Settings!$B$2) | M3: =IF(OR(G3="",J3=""),"",G3-L3-J3-K3-Settings!$B$6) | N3: =IF(M3="","",IF(H3="Y","OK",IF(M3>=Settings!$B$8,"MATCH","HOLD")))
E4: =IF(D4="","",Settings!$B$6) | F4: =IF(D4="","",D4+E4) | I4: =IF(G4="","",G4-Settings!$B$6) | K4: =IF(J4="","",IF(J4<Settings!$B$5,Settings!$B$3,Settings!$B$4)) | L4: =IF(G4="","",G4*Settings!$B$2) | M4: =IF(OR(G4="",J4=""),"",G4-L4-J4-K4-Settings!$B$6) | N4: =IF(M4="","",IF(H4="Y","OK",IF(M4>=Settings!$B$8,"MATCH","HOLD")))
E5: =IF(D5="","",Settings!$B$6) | F5: =IF(D5="","",D5+E5) | I5: =IF(G5="","",G5-Settings!$B$6) | K5: =IF(J5="","",IF(J5<Settings!$B$5,Settings!$B$3,Settings!$B$4)) | L5: =IF(G5="","",G5*Settings!$B$2) | M5: =IF(OR(G5="",J5=""),"",G5-L5-J5-K5-Settings!$B$6) | N5: =IF(M5="","",IF(H5="Y","OK",IF(M5>=Settings!$B$8,"MATCH","HOLD")))
E6: =IF(D6="","",Settings!$B$6) | F6: =IF(D6="","",D6+E6) | I6: =IF(G6="","",G6-Settings!$B$6) | K6: =IF(J6="","",IF(J6<Settings!$B$5,Settings!$B$3,Settings!$B$4)) | L6: =IF(G6="","",G6*Settings!$B$2) | M6: =IF(OR(G6="",J6=""),"",G6-L6-J6-K6-Settings!$B$6) | N6: =IF(M6="","",IF(H6="Y","OK",IF(M6>=Settings!$B$8,"MATCH","HOLD")))
E7: =IF(D7="","",Settings!$B$6) | F7: =IF(D7="","",D7+E7) | I7: =IF(G7="","",G7-Settings!$B$6) | K7: =IF(J7="","",IF(J7<Settings!$B$5,Settings!$B$3,Settings!$B$4)) | L7: =IF(G7="","",G7*Settings!$B$2) | M7: =IF(OR(G7="",J7=""),"",G7-L7-J7-K7-Settings!$B$6) | N7: =IF(M7="","",IF(H7="Y","OK",IF(M7>=Settings!$B$8,"MATCH","HOLD")))
E8: =IF(D8="","",Settings!$B$6) | F8: =IF(D8="","",D8+E8) | I8: =IF(G8="","",G8-Settings!$B$6) | K8: =IF(J8="","",IF(J8<Settings!$B$5,Settings!$B$3,Settings!$B$4)) | L8: =IF(G8="","",G8*Settings!$B$2) | M8: =IF(OR(G8="",J8=""),"",G8-L8-J8-K8-Settings!$B$6) | N8: =IF(M8="","",IF(H8="Y","OK",IF(M8>=Settings!$B$8,"MATCH","HOLD")))
E9: =IF(D9="","",Settings!$B$6) | F9: =IF(D9="","",D9+E9) | I9: =IF(G9="","",G9-Settings!$B$6) | K9: =IF(J9="","",IF(J9<Settings!$B$5,Settings!$B$3,Settings!$B$4)) | L9: =IF(G9="","",G9*Settings!$B$2) | M9: =IF(OR(G9="",J9=""),"",G9-L9-J9-K9-Settings!$B$6) | N9: =IF(M9="","",IF(H9="Y","OK",IF(M9>=Settings!$B$8,"MATCH","HOLD")))
E10: =IF(D10="","",Settings!$B$6) | F10: =IF(D10="","",D10+E10) | I10: =IF(G10="","",G10-Settings!$B$6) | K10: =IF(J10="","",IF(J10<Settings!$B$5,Settings!$B$3,Settings!$B$4)) | L10: =IF(G10="","",G10*Settings!$B$2) | M10: =IF(OR(G10="",J10=""),"",G10-L10-J10-K10-Settings!$B$6) | N10: =IF(M10="","",IF(H10="Y","OK",IF(M10>=Settings!$B$8,"MATCH","HOLD")))
E11: =IF(D11="","",Settings!$B$6) | F11: =IF(D11="","",D11+E11) | I11: =IF(G11="","",G11-Settings!$B$6) | K11: =IF(J11="","",IF(J11<Settings!$B$5,Settings!$B$3,Settings!$B$4)) | L11: =IF(G11="","",G11*Settings!$B$2) | M11: =IF(OR(G11="",J11=""),"",G11-L11-J11-K11-Settings!$B$6) | N11: =IF(M11="","",IF(H11="Y","OK",IF(M11>=Settings!$B$8,"MATCH","HOLD")))
E12: =IF(D12="","",Settings!$B$6) | F12: =IF(D12="","",D12+E12) | I12: =IF(G12="","",G12-Settings!$B$6) | K12: =IF(J12="","",IF(J12<Settings!$B$5,Settings!$B$3,Settings!$B$4)) | L12: =IF(G12="","",G12*Settings!$B$2) | M12: =IF(OR(G12="",J12=""),"",G12-L12-J12-K12-Settings!$B$6) | N12: =IF(M12="","",IF(H12="Y","OK",IF(M12>=Settings!$B$8,"MATCH","HOLD")))
E13: =IF(D13="","",Settings!$B$6) | F13: =IF(D13="","",D13+E13) | I13: =IF(G13="","",G13-Settings!$B$6) | K13: =IF(J13="","",IF(J13<Settings!$B$5,Settings!$B$3,Settings!$B$4)) | L13: =IF(G13="","",G13*Settings!$B$2) | M13: =IF(OR(G13="",J13=""),"",G13-L13-J13-K13-Settings!$B$6) | N13: =IF(M13="","",IF(H13="Y","OK",IF(M13>=Settings!$B$8,"MATCH","HOLD")))
... E401: =IF(D401="","",Settings!$B$6) | F401: =IF(D401="","",D401+E401) | I401: =IF(G401="","",G401-Settings!$B$6) | K401: =IF(J401="","",IF(J401<Settings!$B$5,Settings!$B$3,Settings!$B$4)) | L401: =IF(G401="","",G401*Settings!$B$2) | M401: =IF(OR(G401="",J401=""),"",G401-L401-J401-K401-Settings!$B$6) | N401: =IF(M401="","",IF(H401="Y","OK",IF(M401>=Settings!$B$8,"MATCH","HOLD")))

Sheet Order Log
A1: Amazon order date | B1: Amazon order ID | C1: PO (last 7 digits) | D1: SKU | E1: Qty | F1: Supplier order placed (date) | G1: Supplier reference # | H1: Carrier | I1: Service | J1: Tracking # | K1: Shipment confirmed on Amazon (date) | L1: Days order to confirm | M1: Status | N1: Notes
C2: =IF(B2="","",RIGHT(B2,7)) | L2: =IF(OR(A2="",K2=""),"",K2-A2) | M2: =IF(B2="","",IF(K2<>"","Shipped",IF(F2<>"","Ordered, awaiting tracking","NOT ORDERED")))
C3: =IF(B3="","",RIGHT(B3,7)) | L3: =IF(OR(A3="",K3=""),"",K3-A3) | M3: =IF(B3="","",IF(K3<>"","Shipped",IF(F3<>"","Ordered, awaiting tracking","NOT ORDERED")))
C4: =IF(B4="","",RIGHT(B4,7)) | L4: =IF(OR(A4="",K4=""),"",K4-A4) | M4: =IF(B4="","",IF(K4<>"","Shipped",IF(F4<>"","Ordered, awaiting tracking","NOT ORDERED")))
C5: =IF(B5="","",RIGHT(B5,7)) | L5: =IF(OR(A5="",K5=""),"",K5-A5) | M5: =IF(B5="","",IF(K5<>"","Shipped",IF(F5<>"","Ordered, awaiting tracking","NOT ORDERED")))
C6: =IF(B6="","",RIGHT(B6,7)) | L6: =IF(OR(A6="",K6=""),"",K6-A6) | M6: =IF(B6="","",IF(K6<>"","Shipped",IF(F6<>"","Ordered, awaiting tracking","NOT ORDERED")))
C7: =IF(B7="","",RIGHT(B7,7)) | L7: =IF(OR(A7="",K7=""),"",K7-A7) | M7: =IF(B7="","",IF(K7<>"","Shipped",IF(F7<>"","Ordered, awaiting tracking","NOT ORDERED")))
C8: =IF(B8="","",RIGHT(B8,7)) | L8: =IF(OR(A8="",K8=""),"",K8-A8) | M8: =IF(B8="","",IF(K8<>"","Shipped",IF(F8<>"","Ordered, awaiting tracking","NOT ORDERED")))
C9: =IF(B9="","",RIGHT(B9,7)) | L9: =IF(OR(A9="",K9=""),"",K9-A9) | M9: =IF(B9="","",IF(K9<>"","Shipped",IF(F9<>"","Ordered, awaiting tracking","NOT ORDERED")))
C10: =IF(B10="","",RIGHT(B10,7)) | L10: =IF(OR(A10="",K10=""),"",K10-A10) | M10: =IF(B10="","",IF(K10<>"","Shipped",IF(F10<>"","Ordered, awaiting tracking","NOT ORDERED")))
C11: =IF(B11="","",RIGHT(B11,7)) | L11: =IF(OR(A11="",K11=""),"",K11-A11) | M11: =IF(B11="","",IF(K11<>"","Shipped",IF(F11<>"","Ordered, awaiting tracking","NOT ORDERED")))
C12: =IF(B12="","",RIGHT(B12,7)) | L12: =IF(OR(A12="",K12=""),"",K12-A12) | M12: =IF(B12="","",IF(K12<>"","Shipped",IF(F12<>"","Ordered, awaiting tracking","NOT ORDERED")))
C13: =IF(B13="","",RIGHT(B13,7)) | L13: =IF(OR(A13="",K13=""),"",K13-A13) | M13: =IF(B13="","",IF(K13<>"","Shipped",IF(F13<>"","Ordered, awaiting tracking","NOT ORDERED")))
... C1001: =IF(B1001="","",RIGHT(B1001,7)) | L1001: =IF(OR(A1001="",K1001=""),"",K1001-A1001) | M1001: =IF(B1001="","",IF(K1001<>"","Shipped",IF(F1001<>"","Ordered, awaiting tracking","NOT ORDERED")))

Sheet Monthly Report
A1: Line | B1: Month 1 | C1: Month 2 | D1: Month 3 | E1: Month 4 | F1: Month 5 | G1: Month 6
A2: Orders
A3: Gross sales (customer paid)
A4: Amazon fees
A5: Net deposited by Amazon | B5: =B3-B4 | C5: =C3-C4 | D5: =D3-D4 | E5: =E3-E4 | F5: =F3-F4 | G5: =G3-G4
A6: Supplier cost of those orders
A7: Per-order profit (net minus supplier) | B7: =B5-B6 | C7: =C5-C6 | D7: =D5-D6 | E7: =E5-E6 | F7: =F5-F6 | G7: =G5-G6
A8: Overhead (subscriptions, tools, unrecovered refunds)
A9: BUSINESS PROFIT | B9: =B7-B8 | C9: =C7-C8 | D9: =D7-D8 | E9: =E7-E8 | F9: =F7-F8 | G9: =G7-G8
A10: Net margin on Amazon net revenue | B10: =IF(B5=0,"",B9/B5) | C10: =IF(C5=0,"",C9/C5) | D10: =IF(D5=0,"",D9/D5) | E10: =IF(E5=0,"",E9/E5) | F10: =IF(F5=0,"",F9/F5) | G10: =IF(G5=0,"",G9/G5)
A11: Active listings at month end
A12: Listings where I hold the Featured Offer
A13: ODR %
A14: Late shipment rate %
A15: Cancellation rate %

Sheet 30-Day Plan
A1: Week | B1: Day | C1: Task | D1: Chapter | E1: Done (Y)
A2: 1 | B2: 1 | C2: Register business name; designate bank account; decide GST/HST registration | D2: 2
A3: 1 | B3: 1 | C3: Start Seller Central Professional registration; upload ID | D3: 2
A4: 1 | B4: 2-4 | C4: Shortlist 3 distributors; email the drop-ship questions | D4: 3
A5: 1 | B5: 5 | C5: Open supplier account; place test order to own address | D5: 3
A6: 1 | B6: 6-7 | C6: Build profit spreadsheet with real fees; set and write down the profit floor | D6: 4
A7: 2 | B7: 8 | C7: Build shipping template; set return address | D7: 2
A8: 2 | B8: 8 | C8: Check gating on top 10 brands; apply where needed | D8: 5
A9: 2 | B9: 9-12 | C9: Research by hand, UPC-first; target 80 passes | D9: 5
A10: 2 | B10: 13 | C10: Build bulk upload file; SKU = reorder number; price split; upload | D10: 6
A11: 2 | B11: 14 | C11: Read processing report; fix failures; verify 10 live listings vs Featured Offer | D11: 6
A12: 3 | B12: 15 | C12: Write the order loop as a literal checklist (PO, SKU, carrier names) | D12: 8
A13: 3 | B13: 15-21 | C13: Orders morning and evening; supplier orders same day; confirm on tracking | D13: 8
A14: 3 | B14: 17 | C14: Add 50 more listings | D14: 5
A15: 3 | B15: 21 | C15: First weekly reconciliation | D15: 8
A16: 4 | B16: 22 | C16: Featured Offer audit across all listings; reprice MATCH rows | D16: 7
A17: 4 | B17: 24 | C17: Weekly health check; write 5 message templates | D17: 10
A18: 4 | B18: 26 | C18: Reach 150+ listings | D18: 5
A19: 4 | B19: 28 | C19: Match payments ledger to supplier invoices by PO; monthly report | D19: 11
A20: 4 | B20: 30 | C20: Write the tracking procedure precisely; that is the spec for automation #1 | D20: 9
